massmarket/__init__.py
massmarket/authentication_pb2.py
massmarket/authentication_pb2.pyi
massmarket/base_types_pb2.py
massmarket/base_types_pb2.pyi
massmarket/cbor_encoder.py
massmarket/envelope_pb2.py
massmarket/envelope_pb2.pyi
massmarket/error_pb2.py
massmarket/error_pb2.pyi
massmarket/hamt.py
massmarket/shop_requests_pb2.py
massmarket/shop_requests_pb2.pyi
massmarket/storage_pb2.py
massmarket/storage_pb2.pyi
massmarket/subscription_pb2.py
massmarket/subscription_pb2.pyi
massmarket/transport_pb2.py
massmarket/transport_pb2.pyi
massmarket/cbor/__init__.py
massmarket/cbor/base_types.py
massmarket/cbor/listing.py
massmarket/cbor/manifest.py
massmarket/cbor/order.py
massmarket/cbor/patch.py
massmarket/mmr/README.md
massmarket/mmr/algorithms.py
massmarket/mmr/db.py
massmarket/mmr/tableprint.py
massmarket-4.dist-info/METADATA
massmarket-4.dist-info/WHEEL
massmarket-4.dist-info/top_level.txt
massmarket-4.dist-info/RECORD
