Metadata-Version: 2.4
Name: massmarket
Version: 4
Summary: Helper functions to hash events for signature creation and verification on Mass Market.
Author-email: Henry Bubert <henry@mass.market>
License: MIT
Project-URL: Homepage, https://mass.market
Project-URL: Repository, https://github.com/masslbs/network-schema.git
Classifier: Development Status :: 3 - Alpha
Classifier: License :: OSI Approved :: MIT License
Classifier: Natural Language :: English
Classifier: Operating System :: OS Independent
Classifier: Topic :: Security :: Cryptography
Classifier: Programming Language :: Python :: 3
Classifier: Framework :: Pytest
Classifier: Topic :: Software Development :: Libraries :: Python Modules
Requires-Python: >=3.8
Requires-Dist: web3
Provides-Extra: test
Requires-Dist: pytest; extra == "test"
